openfeature/_backports/__init__.py
openfeature/_backports/strenum.py
openfeature/_event_support.py
openfeature/api.py
openfeature/client.py
openfeature/evaluation_context/__init__.py
openfeature/event.py
openfeature/exception.py
openfeature/flag_evaluation.py
openfeature/hook/__init__.py
openfeature/hook/_hook_support.py
openfeature/immutable_dict/__init__.py
openfeature/immutable_dict/mapping_proxy_type.py
openfeature/provider/__init__.py
openfeature/provider/_registry.py
openfeature/provider/in_memory_provider.py
openfeature/provider/metadata.py
openfeature/provider/no_op_metadata.py
openfeature/provider/no_op_provider.py
openfeature/provider/provider.py
openfeature/py.typed
openfeature/telemetry/__init__.py
openfeature/telemetry/attributes.py
openfeature/telemetry/body.py
openfeature/telemetry/metadata.py
openfeature/transaction_context/__init__.py
openfeature/transaction_context/context_var_transaction_context_propagator.py
openfeature/transaction_context/no_op_transaction_context_propagator.py
openfeature/transaction_context/transaction_context_propagator.py
openfeature/version.py
openfeature_sdk-0.8.4.dist-info/licenses/LICENSE
openfeature_sdk-0.8.4.dist-info/WHEEL
openfeature_sdk-0.8.4.dist-info/entry_points.txt
openfeature_sdk-0.8.4.dist-info/METADATA
openfeature_sdk-0.8.4.dist-info/RECORD
