Metadata-Version: 2.4
Name: openfeature_sdk
Version: 0.8.4
Summary: Standardizing Feature Flagging for Everyone
Keywords: openfeature,feature,flags,toggles
Author: OpenFeature
Author-email: OpenFeature <openfeature-core@groups.io>
License-Expression: Apache-2.0
License-File: LICENSE
Classifier: Programming Language :: Python
Classifier: Programming Language :: Python :: 3
Requires-Python: >=3.9
Project-URL: Homepage, https://github.com/open-feature/python-sdk
